{
  "title": "Questionnaire for Concours Véto PostBac",
  "description": "Questionnaire for Concours Véto PostBac",
  "majorVersion": 1,
  "minorVersion": 0,
  "patchVersion": 14,
  "author": "CALL Learning 2024 (laurent@call-learning.fr)",
  "license": "MIT",
  "machineName": "H5P.ConcoursVeto",
  "fullscreen": 1,
  "runnable": 1,
  "preloadedJs": [
    {
      "path": "dist/h5pconcoursveto.js"
    }
  ],
  "editorDependencies": [
    {
      "machineName": "H5PEditor.VerticalTabs",
      "majorVersion": 1,
      "minorVersion": 3
    }
  ]
}
